{
   "nesi_timer":[
      {
         "hour":2,
         "file_name":[
            "doosi.jpeg"
         ]
      },
      {
         "hour":4,
         "file_name":[
            "nesi.jpg",
            "naesi.jpeg"
         ]
      }
   ],
   "win_whitelist":[

   ],
   "group_list":[
      -142231371,
      -171750445
   ],
   "buy_list":{
      "file_name":[
         "buybuybuy.gif"
      ],
      "filter":[
         "질러",
         "질럿",
         "질렀",
         "지르",
         "지름"
      ]
   },
   "0u":{
      "file_name":[
         "0u.jpg"
      ],
      "filter":[
         "공유"
      ]
   },
   "run_list":{
      "file_name":[
         "where_you_go.jpg"
      ],
      "filter":[
         "퇴근",
         "자러",
         "자야",
         "잔다",
         "잠자",
         "졸려"
      ]
   },
   "onegai":{
      "file_name":[
         "deny_new.jpg"
      ],
      "filter":[
         "해줘",
         "해줭",
         "부탁",
         "오네가이"
      ]
   },
   "podori":{
      "file_name":[
         "yonom.png"
      ],
      "filter":[
         "신고",
         "페도",
         "로리",
         "ㅍㅍㅅㅅ",
         "하앍",
         "헠헠",
         "펔펔",
         "섹스",
         "쎾쓰",
         "sex",
         "세크스"
      ]
   },
   "arrest":{
      "file_name":[
         "ckck.png"
      ],
      "filter":[
         "철컹"
      ]
   }
}